platynui_native/.gitignore
platynui_native/__init__.py
platynui_native/__init__.pyi
platynui_native/__version__.py
platynui_native/_native.pyd
platynui_native/py.typed
robotframework_platynui_native-0.2.0.dev1.dist-info/METADATA
robotframework_platynui_native-0.2.0.dev1.dist-info/WHEEL
robotframework_platynui_native-0.2.0.dev1.dist-info/RECORD
