Metadata-Version: 2.4
Name: robotframework-platynui-native
Version: 0.2.0.dev1
Classifier: Development Status :: 3 - Alpha
Classifier: Intended Audience :: Developers
Classifier: License :: OSI Approved :: Apache Software License
Classifier: Operating System :: OS Independent
Classifier: Programming Language :: Python :: 3
Classifier: Programming Language :: Python :: 3 :: Only
Classifier: Programming Language :: Python :: 3.10
Classifier: Programming Language :: Python :: 3.11
Classifier: Programming Language :: Python :: 3.12
Classifier: Programming Language :: Python :: 3.13
Classifier: Programming Language :: Rust
Classifier: Topic :: Software Development :: Testing
Classifier: Topic :: Software Development :: Quality Assurance
Classifier: Framework :: Robot Framework
Classifier: Framework :: Robot Framework :: Library
Requires-Dist: pytest>=8.0 ; extra == 'dev'
Provides-Extra: dev
Summary: Native Python bindings for PlatynUI (core types + runtime)
Keywords: robotframework,platynui,gui,automation,desktop
Author-email: Daniel Biehl <daniel.biehl@imbus.de>
Maintainer-email: Daniel Biehl <daniel.biehl@imbus.de>
License: Apache-2.0
Requires-Python: >=3.10
Project-URL: Homepage, https://github.com/imbus/robotframework-PlatynUI
Project-URL: Documentation, https://github.com/imbus/robotframework-PlatynUI#readme
Project-URL: Changelog, https://github.com/imbus/robotframework-PlatynUI/blob/main/CHANGELOG.md
Project-URL: Issues, https://github.com/imbus/robotframework-PlatynUI/issues
Project-URL: Source, https://github.com/imbus/robotframework-PlatynUI
